Workbook

Sheet Resumo Gerencial
B3: CHAMADA DE APORTE SEMANAL
B4: Modelo – Resumo Gerencial
B6: GERENCIAMENTO DE OBRAS
B7: Empreendimento: | C7: [NOME DO EMPREENDIMENTO]
B8: CNPJ: | C8: 00.000.000/0001-00
B9: Razão Social: | C9: [RAZÃO SOCIAL DA SPE]
B10: Gestor Vertical: | C10: [NOME DO GESTOR VERTICAL]
B11: Gestor do Contrato: | C11: [NOME DO GESTOR DO CONTRATO]
B13: DADOS DO EMPREENDIMENTO
B14: Empreendimento: | C14: [NOME DO EMPREENDIMENTO]
B15: CNPJ: | C15: 00.000.000/0001-00
B16: Razão Social: | C16: [RAZÃO SOCIAL DA SPE]
B17: Gestor Vertical: | C17: [NOME DO GESTOR VERTICAL]
B18: Gestor do Contrato: | C18: [NOME DO GESTOR DO CONTRATO]
B20: PERÍODO E DATA DO APORTE
B21: Período de Referência (de): | C21: 46238 | D21: até: | E21: 46244
B22: Data do Aporte (descida de recursos):
B24: DADOS BANCÁRIOS PARA DESCIDA DE RECURSOS
B25: Banco: | C25: [BANCO] | D25: Agência: | E25: [AGÊNCIA]
B26: Conta Corrente: | C26: [CONTA CORRENTE] | D26: CNPJ da Conta: | E26: [CNPJ]
B28: RESUMO GERENCIAL DO APORTE
B29: Saldo Bancário | C29: Data: | D29: xx/xx/26
B30: (-) Contas a Pagar – Sistema (já lançadas/pagas no ERP) | E30: =SUMIFS(Tabela1[A_PAGAR], Tabela1[DATA_DE_PAGAMENTO], ">="&C21, Tabela1[DATA_DE_PAGAMENTO], "<="&E21) -> 0
B31: (-) Contas a Lançar – Gerencial (previstas, ainda não lançadas) | E31: =SUM(Tabela3[VALOR PREVISTO]) -> 0
B32: TOTAL DE SAÍDAS DO PERÍODO | E32: =E30+E31 -> 0
B33: (-) Fundo de Reserva
B35: VALOR DO APORTE SOLICITADO
B36: Valor do Aporte Necessário | E36: =E32+E33-E29 -> 0
B38: RATEIO DO APORTE POR INVESTIDOR (opcional)
B39: Investidor / Quotista | D39: % Participação | E39: Valor do Aporte
B40: [Investidor 1] | D40: 1 | E40: =$E$36*D40 -> 0
B41: TOTAL | D41: =SUM(D40:D40) -> 0 | E41: =SUM(E40:E40) -> 0
B43: EXECUÇÃO ORÇAMENTÁRIA (EAP)
B44: Orçamento Alvo Total | E44: ='Controle EAP'!I6 -> 0
B45: Incorrido Acumulado Total (Pago) | E45: ='Controle EAP'!J6 -> 0
B46: Saldo Orçamentário Disponível | E46: =E44-E45 -> 0
B47: % Executado do Orçamento | E47: =E45/E44 -> 0
B51: Legenda:
B52: Amarelo = célula de preenchimento manual
B53: Branco (fórmula) = calculado automaticamente

Sheet CONFIG
B3: {=_xlfn._xlws.FILTER('Controle EAP'!G7:G279,'Controle EAP'!F7:F279=4,"")} -> 01.001.001.001 | C3: {=_xlfn._xlws.FILTER('Controle EAP'!D7:D279,'Controle EAP'!F7:F279=4,"")} -> SERVIÇO DE ELABORAÇÃO DE MANUAL DO PROPRIETÁRIO | D3: =_xlfn.CONCAT(B3,"-",LEFT(C3,100)) -> 01.001.001.001-SERVIÇO DE ELABORAÇÃO DE MANUAL DO PROPRIETÁRIO
B4: 01.001.002.001 | C4: BARRACÕES DE OBRA | D4: =_xlfn.CONCAT(B4,"-",LEFT(C4,100)) -> 01.001.002.001-BARRACÕES DE OBRA
B5: 01.001.002.002 | C5: INSTALAÇÕES PROVISORIAS DE AGUA E ESGOTO | D5: =_xlfn.CONCAT(B5,"-",LEFT(C5,100)) -> 01.001.002.002-INSTALAÇÕES PROVISORIAS DE AGUA E ESGOTO
B6: 01.001.002.003 | C6: INSTALAÇÕES PROVISORIAS DE ENERGIA | D6: =_xlfn.CONCAT(B6,"-",LEFT(C6,100)) -> 01.001.002.003-INSTALAÇÕES PROVISORIAS DE ENERGIA
B7: 01.001.002.004 | C7: SERVIÇO PRESTADO - EQUIPE DE APOIO DE CANTEIRO DE OBRA | D7: =_xlfn.CONCAT(B7,"-",LEFT(C7,100)) -> 01.001.002.004-SERVIÇO PRESTADO - EQUIPE DE APOIO DE CANTEIRO DE OBRA
B8: 01.001.002.005 | C8: SERVIÇO DE EXECUÇÃO DE INSTALAÇÃO DO SISTEMA DE ALARME/SEGURANÇA | D8: =_xlfn.CONCAT(B8,"-",LEFT(C8,100)) -> 01.001.002.005-SERVIÇO DE EXECUÇÃO DE INSTALAÇÃO DO SISTEMA DE ALARME/SEGURANÇA
B9: 01.001.002.006 | C9: SERVIÇO DE MANUTENÇÃO DE ALARME DE SEGURANÇA | D9: =_xlfn.CONCAT(B9,"-",LEFT(C9,100)) -> 01.001.002.006-SERVIÇO DE MANUTENÇÃO DE ALARME DE SEGURANÇA
B10: 01.001.002.007 | C10: INSTALAÇÕES DE CANTEIRO | D10: =_xlfn.CONCAT(B10,"-",LEFT(C10,100)) -> 01.001.002.007-INSTALAÇÕES DE CANTEIRO
B11: 01.001.002.008 | C11: OUTRAS MANUTENÇÕES DE CANTEIRO E SUPORTES TÉCNICOS | D11: =_xlfn.CONCAT(B11,"-",LEFT(C11,100)) -> 01.001.002.008-OUTRAS MANUTENÇÕES DE CANTEIRO E SUPORTES TÉCNICOS
B12: 01.001.002.009 | C12: SERVIÇO DE INSTALAÇÃO DE TAPUME | D12: =_xlfn.CONCAT(B12,"-",LEFT(C12,100)) -> 01.001.002.009-SERVIÇO DE INSTALAÇÃO DE TAPUME
B13: 01.001.002.010 | C13: RETIRADA DE TAPUME | D13: =_xlfn.CONCAT(B13,"-",LEFT(C13,100)) -> 01.001.002.010-RETIRADA DE TAPUME
B14: 01.001.002.011 | C14: SERVIÇO DE SERRALHERIA EM GERAL | D14: =_xlfn.CONCAT(B14,"-",LEFT(C14,100)) -> 01.001.002.011-SERVIÇO DE SERRALHERIA EM GERAL
B15: 01.001.002.012 | C15: TAPUME | D15: =_xlfn.CONCAT(B15,"-",LEFT(C15,100)) -> 01.001.002.012-TAPUME
... B245: 01.002.016.024 | C245: CONCRETO USINADO 25MPA SLUMP12+-2 | D245: =_xlfn.CONCAT(B245,"-",LEFT(C245,100)) -> 01.002.016.024-CONCRETO USINADO 25MPA SLUMP12+-2
B246: 01.002.016.025 | C246: ARGAMASSA COLORIDA PARA SELAR JUNTAS ATÉ 4 MM COR BRANCA COLORSTUK 0-4 BLANCO (HOMOLOGADO)
B247: 01.002.016.026 | C247: ARGAMASSA COLORIDA PARA SELAR JUNTAS ATÉ 4 MM COR MANHATTAN - COLORSTUK 0-4 MANHATTAN N 5 KG (HOMOLOGADO)
B248: 01.002.016.027 | C248: ARGAMASSA COLORIDA PARA SELAR JUNTAS ATÉ 4 MM COR MOKA - COLORSTUK 0-4 MOKA N 5 KG (HOMOLOGADO)
B249: 01.002.016.028 | C249: CRUZETAS AUTONIVELANTES 2MM (1 BOLSA CONTEM 500 CRUZETAS) (HOMOLOGADO)
B250: 01.002.016.029 | C250: CUNHA PARA NIVELAR OS REVESTIMENTOS CERAMICOS (1 BOLSA CONTEM 500 CUNHAS) (HOMOLOGADO)
B251: 01.002.016.030 | C251: FERRAMENTA MANUAL PARA AJUSTE ENTRE CUNHA E CRUZETA PARA NIVELAMENTO DE REVESTIMENTOS CERAMICOS (HOMOLOGADO)

Sheet Controle EAP
B2: CONTROLE EAP - ORÇADO x INCORRIDO ([NOME DA OBRA])
B3: Base: orçamento-alvo enviado (arquivo de orçamento da obra). O incorrido é somado automaticamente a partir da aba Detalhado pelo Código EAP (De-Para).
B5: ITEM_PL | C5: COD_SERVICO | D5: DESCRICAO | E5: TIPO_HIERARQUICO | F5: NIVEL | G5: ITEM | H5: CHAVE | I5: VALOR ORÇADO | J5: VALOR INCORRIDO | K5: SALDO DE ORÇAMENTO
D6: CUSTO OBRA | H6: =IF(F6=4,B6&" - "&C6,"") | I6: =SUMIFS(I:I,$F:$F,1) -> 0 | J6: =SUMIFS(J:J,$F:$F,1) -> 0 | K6: =I6-J6 -> 0
B7: 1 | C7: -1 | D7: OBRA | E7: FASE | F7: 1 | G7: 01 | H7: =IF(F7=4,B7&" - "&C7,"") | I7: =SUMIFS(I:I,$G:$G,'Controle EAP'!G7&"????") -> 0 | J7: =IF(F7=4,SUMIFS(Tabela1[PAGO],Tabela1[CHAVE],'Controle EAP'!H7),SUMIFS(J:J,$G:$G,'Controle EAP'!G7&"????")) -> 0 | K7: =I7-J7 -> 0
B8: 01.01 | C8: -1 | D8: CUSTO INDIRETO DA OBRA | E8: FASE | F8: 2 | G8: 01.001 | H8: =IF(F8=4,B8&" - "&C8,"") | I8: =SUMIFS(I:I,$G:$G,'Controle EAP'!G8&"????") -> 0 | J8: =IF(F8=4,SUMIFS(Tabela1[PAGO],Tabela1[CHAVE],'Controle EAP'!H8),SUMIFS(J:J,$G:$G,'Controle EAP'!G8&"????")) -> 0 | K8: =I8-J8 -> 0
B9: 01.01.01 | C9: -1 | D9: SERVICOS PRELIMINARES E GERAIS | E9: FASE | F9: 3 | G9: 01.001.001 | H9: =IF(F9=4,B9&" - "&C9,"") | I9: =SUMIFS(I:I,$G:$G,'Controle EAP'!G9&"????") -> 0 | J9: =IF(F9=4,SUMIFS(Tabela1[PAGO],Tabela1[CHAVE],'Controle EAP'!H9),SUMIFS(J:J,$G:$G,'Controle EAP'!G9&"????")) -> 0 | K9: =I9-J9 -> 0
B10: 01.01.01.01 | C10: C18612 | D10: SERVIÇO DE ELABORAÇÃO DE MANUAL DO PROPRIETÁRIO | E10: SERVIÇO | F10: 4 | G10: 01.001.001.001 | H10: =IF(F10=4,B10&" - "&C10,"") -> 01.01.01.01 - C18612 | I10: 0 | J10: =IF(F10=4,SUMIFS(Tabela1[PAGO],Tabela1[CHAVE],'Controle EAP'!H10),SUMIFS(J:J,$G:$G,'Controle EAP'!G10&"????")) -> 0 | K10: =I10-J10 -> 0
B11: 01.01.02 | C11: -1 | D11: IMPLANTACAO DA OBRA | E11: FASE | F11: 3 | G11: 01.001.002 | H11: =IF(F11=4,B11&" - "&C11,"") | I11: =SUMIFS(I:I,$G:$G,'Controle EAP'!G11&"????") -> 0 | J11: =IF(F11=4,SUMIFS(Tabela1[PAGO],Tabela1[CHAVE],'Controle EAP'!H11),SUMIFS(J:J,$G:$G,'Controle EAP'!G11&"????")) -> 0 | K11: =I11-J11 -> 0
B12: 01.01.02.01 | C12: C18698 | D12: BARRACÕES DE OBRA | E12: SERVIÇO | F12: 4 | G12: 01.001.002.001 | H12: =IF(F12=4,B12&" - "&C12,"") -> 01.01.02.01 - C18698 | I12: 0 | J12: =IF(F12=4,SUMIFS(Tabela1[PAGO],Tabela1[CHAVE],'Controle EAP'!H12),SUMIFS(J:J,$G:$G,'Controle EAP'!G12&"????")) -> 0 | K12: =I12-J12 -> 0
B13: 01.01.02.02 | C13: C18700 | D13: INSTALAÇÕES PROVISORIAS DE AGUA E ESGOTO | E13: SERVIÇO | F13: 4 | G13: 01.001.002.002 | H13: =IF(F13=4,B13&" - "&C13,"") -> 01.01.02.02 - C18700 | I13: 0 | J13: =IF(F13=4,SUMIFS(Tabela1[PAGO],Tabela1[CHAVE],'Controle EAP'!H13),SUMIFS(J:J,$G:$G,'Controle EAP'!G13&"????")) -> 0 | K13: =I13-J13 -> 0
B14: 01.01.02.03 | C14: C18701 | D14: INSTALAÇÕES PROVISORIAS DE ENERGIA | E14: SERVIÇO | F14: 4 | G14: 01.001.002.003 | H14: =IF(F14=4,B14&" - "&C14,"") -> 01.01.02.03 - C18701 | I14: 0 | J14: =IF(F14=4,SUMIFS(Tabela1[PAGO],Tabela1[CHAVE],'Controle EAP'!H14),SUMIFS(J:J,$G:$G,'Controle EAP'!G14&"????")) -> 0 | K14: =I14-J14 -> 0
B15: 01.01.02.04 | C15: C15897 | D15: SERVIÇO PRESTADO - EQUIPE DE APOIO DE CANTEIRO DE OBRA | E15: SERVIÇO | F15: 4 | G15: 01.001.002.004 | H15: =IF(F15=4,B15&" - "&C15,"") -> 01.01.02.04 - C15897 | I15: 0 | J15: =IF(F15=4,SUMIFS(Tabela1[PAGO],Tabela1[CHAVE],'Controle EAP'!H15),SUMIFS(J:J,$G:$G,'Controle EAP'!G15&"????")) -> 0 | K15: =I15-J15 -> 0
B16: 01.01.02.05 | C16: C19273 | D16: SERVIÇO DE EXECUÇÃO DE INSTALAÇÃO DO SISTEMA DE ALARME/SEGURANÇA | E16: SERVIÇO | F16: 4 | G16: 01.001.002.005 | H16: =IF(F16=4,B16&" - "&C16,"") -> 01.01.02.05 - C19273 | I16: 0 | J16: =IF(F16=4,SUMIFS(Tabela1[PAGO],Tabela1[CHAVE],'Controle EAP'!H16),SUMIFS(J:J,$G:$G,'Controle EAP'!G16&"????")) -> 0 | K16: =I16-J16 -> 0
B17: 01.01.02.06 | C17: C12930 | D17: SERVIÇO DE MANUTENÇÃO DE ALARME DE SEGURANÇA | E17: SERVIÇO | F17: 4 | G17: 01.001.002.006 | H17: =IF(F17=4,B17&" - "&C17,"") -> 01.01.02.06 - C12930 | I17: 0 | J17: =IF(F17=4,SUMIFS(Tabela1[PAGO],Tabela1[CHAVE],'Controle EAP'!H17),SUMIFS(J:J,$G:$G,'Controle EAP'!G17&"????")) -> 0 | K17: =I17-J17 -> 0
B18: 01.01.02.07 | C18: C17211 | D18: INSTALAÇÕES DE CANTEIRO | E18: SERVIÇO | F18: 4 | G18: 01.001.002.007 | H18: =IF(F18=4,B18&" - "&C18,"") -> 01.01.02.07 - C17211 | I18: 0 | J18: =IF(F18=4,SUMIFS(Tabela1[PAGO],Tabela1[CHAVE],'Controle EAP'!H18),SUMIFS(J:J,$G:$G,'Controle EAP'!G18&"????")) -> 0 | K18: =I18-J18 -> 0
B19: 01.01.02.08 | C19: CO330 | D19: OUTRAS MANUTENÇÕES DE CANTEIRO E SUPORTES TÉCNICOS | E19: SERVIÇO | F19: 4 | G19: 01.001.002.008 | H19: =IF(F19=4,B19&" - "&C19,"") -> 01.01.02.08 - CO330 | I19: 0 | J19: =IF(F19=4,SUMIFS(Tabela1[PAGO],Tabela1[CHAVE],'Controle EAP'!H19),SUMIFS(J:J,$G:$G,'Controle EAP'!G19&"????")) -> 0 | K19: =I19-J19 -> 0
B20: 01.01.02.09 | C20: C12643 | D20: SERVIÇO DE INSTALAÇÃO DE TAPUME | E20: SERVIÇO | F20: 4 | G20: 01.001.002.009 | H20: =IF(F20=4,B20&" - "&C20,"") -> 01.01.02.09 - C12643 | I20: 0 | J20: =IF(F20=4,SUMIFS(Tabela1[PAGO],Tabela1[CHAVE],'Controle EAP'!H20),SUMIFS(J:J,$G:$G,'Controle EAP'!G20&"????")) -> 0 | K20: =I20-J20 -> 0
B21: 01.01.02.11 | C21: C19930 | D21: RETIRADA DE TAPUME | E21: SERVIÇO | F21: 4 | G21: 01.001.002.010 | H21: =IF(F21=4,B21&" - "&C21,"") -> 01.01.02.11 - C19930 | I21: 0 | J21: =IF(F21=4,SUMIFS(Tabela1[PAGO],Tabela1[CHAVE],'Controle EAP'!H21),SUMIFS(J:J,$G:$G,'Controle EAP'!G21&"????")) -> 0 | K21: =I21-J21 -> 0
B22: 01.01.02.13 | C22: C15008 | D22: SERVIÇO DE SERRALHERIA EM GERAL | E22: SERVIÇO | F22: 4 | G22: 01.001.002.011 | H22: =IF(F22=4,B22&" - "&C22,"") -> 01.01.02.13 - C15008 | I22: 0 | J22: =IF(F22=4,SUMIFS(Tabela1[PAGO],Tabela1[CHAVE],'Controle EAP'!H22),SUMIFS(J:J,$G:$G,'Controle EAP'!G22&"????")) -> 0 | K22: =I22-J22 -> 0
B23: 01.01.02.14 | C23: C15194 | D23: TAPUME | E23: SERVIÇO | F23: 4 | G23: 01.001.002.012 | H23: =IF(F23=4,B23&" - "&C23,"") -> 01.01.02.14 - C15194 | I23: 0 | J23: =IF(F23=4,SUMIFS(Tabela1[PAGO],Tabela1[CHAVE],'Controle EAP'!H23),SUMIFS(J:J,$G:$G,'Controle EAP'!G23&"????")) -> 0 | K23: =I23-J23 -> 0
... B25: 01.01.02.17 | C25: C18702 | D25: PLACAS DE OBRA | E25: SERVIÇO | F25: 4 | G25: 01.001.002.014 | H25: =IF(F25=4,B25&" - "&C25,"") -> 01.01.02.17 - C18702 | I25: 0 | J25: =IF(F25=4,SUMIFS(Tabela1[PAGO],Tabela1[CHAVE],'Controle EAP'!H25),SUMIFS(J:J,$G:$G,'Controle EAP'!G25&"????")) -> 0 | K25: =I25-J25 -> 0
B26: 01.01.03 | C26: -1 | D26: EQUIPAMENTOS/FERRAMENTAS | E26: FASE | F26: 3 | G26: 01.001.003 | H26: =IF(F26=4,B26&" - "&C26,"") | I26: =SUMIFS(I:I,$G:$G,'Controle EAP'!G26&"????") -> 0 | J26: =IF(F26=4,SUMIFS(Tabela1[PAGO],Tabela1[CHAVE],'Controle EAP'!H26),SUMIFS(J:J,$G:$G,'Controle EAP'!G26&"????")) -> 0 | K26: =I26-J26 -> 0
B27: 01.01.03.01 | C27: C17519 | D27: SERVIÇO DE MANUTENÇÃO DE CONTROLE DE AR CONDICIONADO | E27: SERVIÇO | F27: 4 | G27: 01.001.003.001 | H27: =IF(F27=4,B27&" - "&C27,"") -> 01.01.03.01 - C17519 | I27: 0 | J27: =IF(F27=4,SUMIFS(Tabela1[PAGO],Tabela1[CHAVE],'Controle EAP'!H27),SUMIFS(J:J,$G:$G,'Controle EAP'!G27&"????")) -> 0 | K27: =I27-J27 -> 0
B28: 01.01.03.02 | C28: C14888 | D28: SERVIÇO DE INSTALAÇÃO DE BEBEDOUROS | E28: SERVIÇO | F28: 4 | G28: 01.001.003.002 | H28: =IF(F28=4,B28&" - "&C28,"") -> 01.01.03.02 - C14888 | I28: 0 | J28: =IF(F28=4,SUMIFS(Tabela1[PAGO],Tabela1[CHAVE],'Controle EAP'!H28),SUMIFS(J:J,$G:$G,'Controle EAP'!G28&"????")) -> 0 | K28: =I28-J28 -> 0
B29: 01.01.03.03 | C29: C11595 | D29: LOCAÇÃO DIÁRIA DE BETONEIRA 320LT A 400LT SEM CARREGADO R - ALIMENTAÇÃO: ENERGIA ELÉTRICA | E29: SERVIÇO | F29: 4 | G29: 01.001.003.003 | H29: =IF(F29=4,B29&" - "&C29,"") -> 01.01.03.03 - C11595 | I29: 0 | J29: =IF(F29=4,SUMIFS(Tabela1[PAGO],Tabela1[CHAVE],'Controle EAP'!H29),SUMIFS(J:J,$G:$G,'Controle EAP'!G29&"????")) -> 0 | K29: =I29-J29 -> 0
B30: 01.01.03.04 | C30: C18296 | D30: SERVIÇO DE MANUTENÇÃO CORRETIVA DE FURADEIRA | E30: SERVIÇO | F30: 4 | G30: 01.001.003.004 | H30: =IF(F30=4,B30&" - "&C30,"") -> 01.01.03.04 - C18296 | I30: 0 | J30: =IF(F30=4,SUMIFS(Tabela1[PAGO],Tabela1[CHAVE],'Controle EAP'!H30),SUMIFS(J:J,$G:$G,'Controle EAP'!G30&"????")) -> 0 | K30: =I30-J30 -> 0
B31: 01.01.03.05 | C31: C18363 | D31: SERVIÇO DE LAVANDERIA - CAPAS PARA LAVAR | E31: SERVIÇO | F31: 4 | G31: 01.001.003.005 | H31: =IF(F31=4,B31&" - "&C31,"") -> 01.01.03.05 - C18363 | I31: 0 | J31: =IF(F31=4,SUMIFS(Tabela1[PAGO],Tabela1[CHAVE],'Controle EAP'!H31),SUMIFS(J:J,$G:$G,'Controle EAP'!G31&"????")) -> 0 | K31: =I31-J31 -> 0
B32: 01.01.03.06 | C32: C18411 | D32: CORTE DE VIDRO PARA ESTRUTURA METÁLICA | E32: SERVIÇO | F32: 4 | G32: 01.001.003.006 | H32: =IF(F32=4,B32&" - "&C32,"") -> 01.01.03.06 - C18411 | I32: 0 | J32: =IF(F32=4,SUMIFS(Tabela1[PAGO],Tabela1[CHAVE],'Controle EAP'!H32),SUMIFS(J:J,$G:$G,'Controle EAP'!G32&"????")) -> 0 | K32: =I32-J32 -> 0
B33: 01.01.03.07 | C33: C00767 | D33: LAZER | E33: SERVIÇO | F33: 4 | G33: 01.001.003.007 | H33: =IF(F33=4,B33&" - "&C33,"") -> 01.01.03.07 - C00767 | I33: 0 | J33: =IF(F33=4,SUMIFS(Tabela1[PAGO],Tabela1[CHAVE],'Controle EAP'!H33),SUMIFS(J:J,$G:$G,'Controle EAP'!G33&"????")) -> 0 | K33: =I33-J33 -> 0
B34: 01.01.03.08 | C34: C18114 | D34: SERVIÇO DE MANUTENÇÃO DE PISTOLA FINCA PIN | E34: SERVIÇO | F34: 4 | G34: 01.001.003.008 | H34: =IF(F34=4,B34&" - "&C34,"") -> 01.01.03.08 - C18114 | I34: 0 | J34: =IF(F34=4,SUMIFS(Tabela1[PAGO],Tabela1[CHAVE],'Controle EAP'!H34),SUMIFS(J:J,$G:$G,'Controle EAP'!G34&"????")) -> 0 | K34: =I34-J34 -> 0
B35: 01.01.03.09 | C35: C11639 | D35: LOCAÇÃO DIÁRIA DE POLICORTE - ALIMENTAÇÃO: ENERGIA ELÉTRICA | E35: SERVIÇO | F35: 4 | G35: 01.001.003.009 | H35: =IF(F35=4,B35&" - "&C35,"") -> 01.01.03.09 - C11639 | I35: 0 | J35: =IF(F35=4,SUMIFS(Tabela1[PAGO],Tabela1[CHAVE],'Controle EAP'!H35),SUMIFS(J:J,$G:$G,'Controle EAP'!G35&"????")) -> 0 | K35: =I35-J35 -> 0
B36: 01.01.03.10 | C36: C18389 | D36: LOCAÇÃO DE RADIO COMUNICADOR | E36: SERVIÇO | F36: 4 | G36: 01.001.003.010 | H36: =IF(F36=4,B36&" - "&C36,"") -> 01.01.03.10 - C18389 | I36: 0 | J36: =IF(F36=4,SUMIFS(Tabela1[PAGO],Tabela1[CHAVE],'Controle EAP'!H36),SUMIFS(J:J,$G:$G,'Controle EAP'!G36&"????")) -> 0 | K36: =I36-J36 -> 0
B37: 01.01.03.11 | C37: C12852 | D37: SERVIÇO DE MANUTENÇÃO / CONSERTO - SERRA CIRCULAR | E37: SERVIÇO | F37: 4 | G37: 01.001.003.011 | H37: =IF(F37=4,B37&" - "&C37,"") -> 01.01.03.11 - C12852 | I37: 0 | J37: =IF(F37=4,SUMIFS(Tabela1[PAGO],Tabela1[CHAVE],'Controle EAP'!H37),SUMIFS(J:J,$G:$G,'Controle EAP'!G37&"????")) -> 0 | K37: =I37-J37 -> 0
B38: 01.01.03.12 | C38: C17641 | D38: LOCAÇÃO DE MARTELETE ROMPEDOR 7KG | E38: SERVIÇO | F38: 4 | G38: 01.001.003.012 | H38: =IF(F38=4,B38&" - "&C38,"") -> 01.01.03.12 - C17641 | I38: 0 | J38: =IF(F38=4,SUMIFS(Tabela1[PAGO],Tabela1[CHAVE],'Controle EAP'!H38),SUMIFS(J:J,$G:$G,'Controle EAP'!G38&"????")) -> 0 | K38: =I38-J38 -> 0
... B51: 01.01.03.25 | C51: CO608 | D51: BAIA PARA PRODUTOS RECICLAVEIS | E51: SERVIÇO | F51: 4 | G51: 01.001.003.025 | H51: =IF(F51=4,B51&" - "&C51,"") -> 01.01.03.25 - CO608 | I51: 0 | J51: =IF(F51=4,SUMIFS(Tabela1[PAGO],Tabela1[CHAVE],'Controle EAP'!H51),SUMIFS(J:J,$G:$G,'Controle EAP'!G51&"????")) -> 0 | K51: =I51-J51 -> 0
B52: 01.01.04 | C52: -1 | D52: CUSTOS ADMINISTRATIVOS | E52: FASE | F52: 3 | G52: 01.001.004 | H52: =IF(F52=4,B52&" - "&C52,"") | I52: =SUMIFS(I:I,$G:$G,'Controle EAP'!G52&"????") -> 0 | J52: =IF(F52=4,SUMIFS(Tabela1[PAGO],Tabela1[CHAVE],'Controle EAP'!H52),SUMIFS(J:J,$G:$G,'Controle EAP'!G52&"????")) -> 0 | K52: =I52-J52 -> 0
B53: 01.01.04.01 | C53: CO614 | D53: MESTRE DE OBRAS | E53: SERVIÇO | F53: 4 | G53: 01.001.004.001 | H53: =IF(F53=4,B53&" - "&C53,"") -> 01.01.04.01 - CO614 | I53: 0 | J53: =IF(F53=4,SUMIFS(Tabela1[PAGO],Tabela1[CHAVE],'Controle EAP'!H53),SUMIFS(J:J,$G:$G,'Controle EAP'!G53&"????")) -> 0 | K53: =I53-J53 -> 0
B54: 01.01.04.02 | C54: CO454 | D54: GERENTE DE OBRA | E54: SERVIÇO | F54: 4 | G54: 01.001.004.002 | H54: =IF(F54=4,B54&" - "&C54,"") -> 01.01.04.02 - CO454 | I54: 0 | J54: =IF(F54=4,SUMIFS(Tabela1[PAGO],Tabela1[CHAVE],'Controle EAP'!H54),SUMIFS(J:J,$G:$G,'Controle EAP'!G54&"????")) -> 0 | K54: =I54-J54 -> 0
B55: 01.01.04.03 | C55: CO616 | D55: ALMOXARIFE / ADMINISTRATIVO | E55: SERVIÇO | F55: 4 | G55: 01.001.004.003 | H55: =IF(F55=4,B55&" - "&C55,"") -> 01.01.04.03 - CO616 | I55: 0 | J55: =IF(F55=4,SUMIFS(Tabela1[PAGO],Tabela1[CHAVE],'Controle EAP'!H55),SUMIFS(J:J,$G:$G,'Controle EAP'!G55&"????")) -> 0 | K55: =I55-J55 -> 0
B56: 01.01.04.04 | C56: CO618 | D56: TÉCNICO DE SEGURANÇA | E56: SERVIÇO | F56: 4 | G56: 01.001.004.004 | H56: =IF(F56=4,B56&" - "&C56,"") -> 01.01.04.04 - CO618 | I56: 0 | J56: =IF(F56=4,SUMIFS(Tabela1[PAGO],Tabela1[CHAVE],'Controle EAP'!H56),SUMIFS(J:J,$G:$G,'Controle EAP'!G56&"????")) -> 0 | K56: =I56-J56 -> 0
B57: 01.01.04.05 | C57: CO650 | D57: ENCARREGADO ACABAMENTO | E57: SERVIÇO | F57: 4 | G57: 01.001.004.005 | H57: =IF(F57=4,B57&" - "&C57,"") -> 01.01.04.05 - CO650 | I57: 0 | J57: =IF(F57=4,SUMIFS(Tabela1[PAGO],Tabela1[CHAVE],'Controle EAP'!H57),SUMIFS(J:J,$G:$G,'Controle EAP'!G57&"????")) -> 0 | K57: =I57-J57 -> 0
B58: 01.01.04.06 | C58: C12370 | D58: MÃO DE OBRA - PORTEIRO | E58: SERVIÇO | F58: 4 | G58: 01.001.004.006 | H58: =IF(F58=4,B58&" - "&C58,"") -> 01.01.04.06 - C12370 | I58: 0 | J58: =IF(F58=4,SUMIFS(Tabela1[PAGO],Tabela1[CHAVE],'Controle EAP'!H58),SUMIFS(J:J,$G:$G,'Controle EAP'!G58&"????")) -> 0 | K58: =I58-J58 -> 0
B59: 01.01.04.07 | C59: C15076 | D59: SERVIÇO DE VIGILÂNCIA / PORTARIA (NOTURNO) | E59: SERVIÇO | F59: 4 | G59: 01.001.004.007 | H59: =IF(F59=4,B59&" - "&C59,"") -> 01.01.04.07 - C15076 | I59: 0 | J59: =IF(F59=4,SUMIFS(Tabela1[PAGO],Tabela1[CHAVE],'Controle EAP'!H59),SUMIFS(J:J,$G:$G,'Controle EAP'!G59&"????")) -> 0 | K59: =I59-J59 -> 0
B60: 01.01.04.08 | C60: C19701 | D60: SERVIÇO PRESTADO - EQUIPE ADMINISTRATIVA EM CANTEIRO DE OBRA | E60: SERVIÇO | F60: 4 | G60: 01.001.004.008 | H60: =IF(F60=4,B60&" - "&C60,"") -> 01.01.04.08 - C19701 | I60: 0 | J60: =IF(F60=4,SUMIFS(Tabela1[PAGO],Tabela1[CHAVE],'Controle EAP'!H60),SUMIFS(J:J,$G:$G,'Controle EAP'!G60&"????")) -> 0 | K60: =I60-J60 -> 0
B61: 01.01.04.09 | C61: C19642 | D61: MÃO DE OBRA - SERVENTE | E61: SERVIÇO | F61: 4 | G61: 01.001.004.009 | H61: =IF(F61=4,B61&" - "&C61,"") -> 01.01.04.09 - C19642 | I61: 0 | J61: =IF(F61=4,SUMIFS(Tabela1[PAGO],Tabela1[CHAVE],'Controle EAP'!H61),SUMIFS(J:J,$G:$G,'Controle EAP'!G61&"????")) -> 0 | K61: =I61-J61 -> 0
B62: 01.01.04.10 | C62: CO639 | D62: OPERADOR DE BETONEIRA | E62: SERVIÇO | F62: 4 | G62: 01.001.004.010 | H62: =IF(F62=4,B62&" - "&C62,"") -> 01.01.04.10 - CO639 | I62: 0 | J62: =IF(F62=4,SUMIFS(Tabela1[PAGO],Tabela1[CHAVE],'Controle EAP'!H62),SUMIFS(J:J,$G:$G,'Controle EAP'!G62&"????")) -> 0 | K62: =I62-J62 -> 0
B63: 01.01.04.11 | C63: CO329 | D63: MATERIAIS DE EXPEDIENTE E LIMPEZA | E63: SERVIÇO | F63: 4 | G63: 01.001.004.011 | H63: =IF(F63=4,B63&" - "&C63,"") -> 01.01.04.11 - CO329 | I63: 0 | J63: =IF(F63=4,SUMIFS(Tabela1[PAGO],Tabela1[CHAVE],'Controle EAP'!H63),SUMIFS(J:J,$G:$G,'Controle EAP'!G63&"????")) -> 0 | K63: =I63-J63 -> 0
B64: 01.01.04.12 | C64: C19760 | D64: SERVIÇO DE ANALISTA DE OBRA | E64: SERVIÇO | F64: 4 | G64: 01.001.004.012 | H64: =IF(F64=4,B64&" - "&C64,"") -> 01.01.04.12 - C19760 | I64: 0 | J64: =IF(F64=4,SUMIFS(Tabela1[PAGO],Tabela1[CHAVE],'Controle EAP'!H64),SUMIFS(J:J,$G:$G,'Controle EAP'!G64&"????")) -> 0 | K64: =I64-J64 -> 0
... B78: 01.01.04.26 | C78: C15694 | D78: SSMA - SERVIÇO DE ELABORAÇÃO LTCAT (LAUDO TÉCNICO DE CONDIÇÕES AMBIENTAIS DO TRABALHO) | E78: SERVIÇO | F78: 4 | G78: 01.001.004.026 | H78: =IF(F78=4,B78&" - "&C78,"") -> 01.01.04.26 - C15694 | I78: 0 | J78: =IF(F78=4,SUMIFS(Tabela1[PAGO],Tabela1[CHAVE],'Controle EAP'!H78),SUMIFS(J:J,$G:$G,'Controle EAP'!G78&"????")) -> 0 | K78: =I78-J78 -> 0
B79: 01.01.05 | C79: -1 | D79: LIMPEZA E DESMOBILIZACAO | E79: FASE | F79: 3 | G79: 01.001.005 | H79: =IF(F79=4,B79&" - "&C79,"") | I79: =SUMIFS(I:I,$G:$G,'Controle EAP'!G79&"????") -> 0 | J79: =IF(F79=4,SUMIFS(Tabela1[PAGO],Tabela1[CHAVE],'Controle EAP'!H79),SUMIFS(J:J,$G:$G,'Controle EAP'!G79&"????")) -> 0 | K79: =I79-J79 -> 0
B80: 01.01.05.01 | C80: C17654 | D80: FORNECIMENTO DE CAÇAMBA PARA TRANSPORTE DE ENTULHO | E80: SERVIÇO | F80: 4 | G80: 01.001.005.001 | H80: =IF(F80=4,B80&" - "&C80,"") -> 01.01.05.01 - C17654 | I80: 0 | J80: =IF(F80=4,SUMIFS(Tabela1[PAGO],Tabela1[CHAVE],'Controle EAP'!H80),SUMIFS(J:J,$G:$G,'Controle EAP'!G80&"????")) -> 0 | K80: =I80-J80 -> 0
B81: 01.01.05.02 | C81: C17528 | D81: LIMPEZA E DRENAGEM DE VIAS FLUVIAIS | E81: SERVIÇO | F81: 4 | G81: 01.001.005.002 | H81: =IF(F81=4,B81&" - "&C81,"") -> 01.01.05.02 - C17528 | I81: 0 | J81: =IF(F81=4,SUMIFS(Tabela1[PAGO],Tabela1[CHAVE],'Controle EAP'!H81),SUMIFS(J:J,$G:$G,'Controle EAP'!G81&"????")) -> 0 | K81: =I81-J81 -> 0
B82: 01.02 | C82: -1 | D82: CUSTOS DIRETOS | E82: FASE | F82: 2 | G82: 01.002 | H82: =IF(F82=4,B82&" - "&C82,"") | I82: =SUMIFS(I:I,$G:$G,'Controle EAP'!G82&"????") -> 0 | J82: =IF(F82=4,SUMIFS(Tabela1[PAGO],Tabela1[CHAVE],'Controle EAP'!H82),SUMIFS(J:J,$G:$G,'Controle EAP'!G82&"????")) -> 0 | K82: =I82-J82 -> 0
B83: 01.02.00 | C83: -1 | D83: DEMOLIÇÕES GERAIS | E83: FASE | F83: 3 | G83: 01.002.001 | H83: =IF(F83=4,B83&" - "&C83,"") | I83: =SUMIFS(I:I,$G:$G,'Controle EAP'!G83&"????") -> 0 | J83: =IF(F83=4,SUMIFS(Tabela1[PAGO],Tabela1[CHAVE],'Controle EAP'!H83),SUMIFS(J:J,$G:$G,'Controle EAP'!G83&"????")) -> 0 | K83: =I83-J83 -> 0
B84: 01.02.00.03 | C84: CSF7.04 | D84: DEMOLIÇÃO. | E84: SERVIÇO | F84: 4 | G84: 01.002.001.001 | H84: =IF(F84=4,B84&" - "&C84,"") -> 01.02.00.03 - CSF7.04 | I84: 0 | J84: =IF(F84=4,SUMIFS(Tabela1[PAGO],Tabela1[CHAVE],'Controle EAP'!H84),SUMIFS(J:J,$G:$G,'Controle EAP'!G84&"????")) -> 0 | K84: =I84-J84 -> 0
B85: 01.02.02 | C85: -1 | D85: MOVIMENTO DE TERRA | E85: FASE | F85: 3 | G85: 01.002.002 | H85: =IF(F85=4,B85&" - "&C85,"") | I85: =SUMIFS(I:I,$G:$G,'Controle EAP'!G85&"????") -> 0 | J85: =IF(F85=4,SUMIFS(Tabela1[PAGO],Tabela1[CHAVE],'Controle EAP'!H85),SUMIFS(J:J,$G:$G,'Controle EAP'!G85&"????")) -> 0 | K85: =I85-J85 -> 0
B86: 01.02.02.01 | C86: C17788 | D86: FORNECIMENTO, CARGA E TRANSPORTE DE MATERIAL 1ª CATEGORIA | E86: SERVIÇO | F86: 4 | G86: 01.002.002.001 | H86: =IF(F86=4,B86&" - "&C86,"") -> 01.02.02.01 - C17788 | I86: 0 | J86: =IF(F86=4,SUMIFS(Tabela1[PAGO],Tabela1[CHAVE],'Controle EAP'!H86),SUMIFS(J:J,$G:$G,'Controle EAP'!G86&"????")) -> 0 | K86: =I86-J86 -> 0
B87: 01.02.02.02 | C87: C18662 | D87: LOCAÇÃO MENSAL DE RETROESCAVADEIRA COM OPERADOR / DIESEL | E87: SERVIÇO | F87: 4 | G87: 01.002.002.002 | H87: =IF(F87=4,B87&" - "&C87,"") -> 01.02.02.02 - C18662 | I87: 0 | J87: =IF(F87=4,SUMIFS(Tabela1[PAGO],Tabela1[CHAVE],'Controle EAP'!H87),SUMIFS(J:J,$G:$G,'Controle EAP'!G87&"????")) -> 0 | K87: =I87-J87 -> 0
B88: 01.02.03 | C88: -1 | D88: INFRA-ESTRUTURA | E88: FASE | F88: 3 | G88: 01.002.003 | H88: =IF(F88=4,B88&" - "&C88,"") | I88: =SUMIFS(I:I,$G:$G,'Controle EAP'!G88&"????") -> 0 | J88: =IF(F88=4,SUMIFS(Tabela1[PAGO],Tabela1[CHAVE],'Controle EAP'!H88),SUMIFS(J:J,$G:$G,'Controle EAP'!G88&"????")) -> 0 | K88: =I88-J88 -> 0
B89: 01.02.03.01 | C89: C17174 | D89: MOBILIZAÇÃO DE EQUIPAMENTOS | E89: SERVIÇO | F89: 4 | G89: 01.002.003.001 | H89: =IF(F89=4,B89&" - "&C89,"") -> 01.02.03.01 - C17174 | I89: 0 | J89: =IF(F89=4,SUMIFS(Tabela1[PAGO],Tabela1[CHAVE],'Controle EAP'!H89),SUMIFS(J:J,$G:$G,'Controle EAP'!G89&"????")) -> 0 | K89: =I89-J89 -> 0
B90: 01.02.03.02 | C90: CO000061 | D90: SERVICO DE ESCAVACAO DE ESTACA CONVENCIONAL MECANICAMENTE - DIAM 30CM | E90: SERVIÇO | F90: 4 | G90: 01.002.003.002 | H90: =IF(F90=4,B90&" - "&C90,"") -> 01.02.03.02 - CO000061 | I90: 0 | J90: =IF(F90=4,SUMIFS(Tabela1[PAGO],Tabela1[CHAVE],'Controle EAP'!H90),SUMIFS(J:J,$G:$G,'Controle EAP'!G90&"????")) -> 0 | K90: =I90-J90 -> 0
B91: 01.02.03.03 | C91: CO061 | D91: RETIRADA DE MATERIAL DE BOTA FORA | E91: SERVIÇO | F91: 4 | G91: 01.002.003.003 | H91: =IF(F91=4,B91&" - "&C91,"") -> 01.02.03.03 - CO061 | I91: 0 | J91: =IF(F91=4,SUMIFS(Tabela1[PAGO],Tabela1[CHAVE],'Controle EAP'!H91),SUMIFS(J:J,$G:$G,'Controle EAP'!G91&"????")) -> 0 | K91: =I91-J91 -> 0
B92: 01.02.03.04 | C92: C14578 | D92: SERVIÇO DE FUNDAÇÃO - PREPARAÇÃO DA CABEÇA DA ESTACA METÁLICA | E92: SERVIÇO | F92: 4 | G92: 01.002.003.004 | H92: =IF(F92=4,B92&" - "&C92,"") -> 01.02.03.04 - C14578 | I92: 0 | J92: =IF(F92=4,SUMIFS(Tabela1[PAGO],Tabela1[CHAVE],'Controle EAP'!H92),SUMIFS(J:J,$G:$G,'Controle EAP'!G92&"????")) -> 0 | K92: =I92-J92 -> 0
B93: 01.02.03.05 | C93: CO854 | D93: SERVIÇO DE PREPARAÇÃO DE CORTE E REPARO EM ESTACAS | E93: SERVIÇO | F93: 4 | G93: 01.002.003.005 | H93: =IF(F93=4,B93&" - "&C93,"") -> 01.02.03.05 - CO854 | I93: 0 | J93: =IF(F93=4,SUMIFS(Tabela1[PAGO],Tabela1[CHAVE],'Controle EAP'!H93),SUMIFS(J:J,$G:$G,'Controle EAP'!G93&"????")) -> 0 | K93: =I93-J93 -> 0
B94: 01.02.03.06 | C94: CO000007 | D94: CONCRETO USINADO 25MPA - SLUMP 14±2 - BRITA 0 - COM ½ ADITIVO (ADITIVO POLIFUNCIONAL) - NBR 12655 | E94: SERVIÇO | F94: 4 | G94: 01.002.003.006 | H94: =IF(F94=4,B94&" - "&C94,"") -> 01.02.03.06 - CO000007 | I94: 0 | J94: =IF(F94=4,SUMIFS(Tabela1[PAGO],Tabela1[CHAVE],'Controle EAP'!H94),SUMIFS(J:J,$G:$G,'Controle EAP'!G94&"????")) -> 0 | K94: =I94-J94 -> 0
B95: 01.02.03.07 | C95: CO441 | D95: LANÇAMENTO DE CONCRETO | E95: SERVIÇO | F95: 4 | G95: 01.002.003.007 | H95: =IF(F95=4,B95&" - "&C95,"") -> 01.02.03.07 - CO441 | I95: 0 | J95: =IF(F95=4,SUMIFS(Tabela1[PAGO],Tabela1[CHAVE],'Controle EAP'!H95),SUMIFS(J:J,$G:$G,'Controle EAP'!G95&"????")) -> 0 | K95: =I95-J95 -> 0
B96: 01.02.03.08 | C96: CO253 | D96: CONTROLE TECNOLOGICO DO CONCRETO (ESTRUTURA) | E96: SERVIÇO | F96: 4 | G96: 01.002.003.008 | H96: =IF(F96=4,B96&" - "&C96,"") -> 01.02.03.08 - CO253 | I96: 0 | J96: =IF(F96=4,SUMIFS(Tabela1[PAGO],Tabela1[CHAVE],'Controle EAP'!H96),SUMIFS(J:J,$G:$G,'Controle EAP'!G96&"????")) -> 0 | K96: =I96-J96 -> 0
B97: 01.02.03.09 | C97: C18726 | D97: RETROESCAVADEIRA | E97: SERVIÇO | F97: 4 | G97: 01.002.003.009 | H97: =IF(F97=4,B97&" - "&C97,"") -> 01.02.03.09 - C18726 | I97: 0 | J97: =IF(F97=4,SUMIFS(Tabela1[PAGO],Tabela1[CHAVE],'Controle EAP'!H97),SUMIFS(J:J,$G:$G,'Controle EAP'!G97&"????")) -> 0 | K97: =I97-J97 -> 0
B98: 01.02.03.10 | C98: CO056 | D98: ESCAVAÇÃO MANUAL DE BLOCOS | E98: SERVIÇO | F98: 4 | G98: 01.002.003.010 | H98: =IF(F98=4,B98&" - "&C98,"") -> 01.02.03.10 - CO056 | I98: 0 | J98: =IF(F98=4,SUMIFS(Tabela1[PAGO],Tabela1[CHAVE],'Controle EAP'!H98),SUMIFS(J:J,$G:$G,'Controle EAP'!G98&"????")) -> 0 | K98: =I98-J98 -> 0
B99: 01.02.03.11 | C99: CO062 | D99: REATERRO COMPACTADO | E99: SERVIÇO | F99: 4 | G99: 01.002.003.011 | H99: =IF(F99=4,B99&" - "&C99,"") -> 01.02.03.11 - CO062 | I99: 0 | J99: =IF(F99=4,SUMIFS(Tabela1[PAGO],Tabela1[CHAVE],'Controle EAP'!H99),SUMIFS(J:J,$G:$G,'Controle EAP'!G99&"????")) -> 0 | K99: =I99-J99 -> 0
B100: 01.02.03.12 | C100: CO061 | D100: RETIRADA DE MATERIAL DE BOTA FORA | E100: SERVIÇO | F100: 4 | G100: 01.002.003.012 | H100: =IF(F100=4,B100&" - "&C100,"") -> 01.02.03.12 - CO061 | I100: 0 | J100: =IF(F100=4,SUMIFS(Tabela1[PAGO],Tabela1[CHAVE],'Controle EAP'!H100),SUMIFS(J:J,$G:$G,'Controle EAP'!G100&"????")) -> 0 | K100: =I100-J100 -> 0
... B105: 01.02.03.17 | C105: CO441 | D105: LANÇAMENTO DE CONCRETO | E105: SERVIÇO | F105: 4 | G105: 01.002.003.017 | H105: =IF(F105=4,B105&" - "&C105,"") -> 01.02.03.17 - CO441 | I105: 0 | J105: =IF(F105=4,SUMIFS(Tabela1[PAGO],Tabela1[CHAVE],'Controle EAP'!H105),SUMIFS(J:J,$G:$G,'Controle EAP'!G105&"????")) -> 0 | K105: =I105-J105 -> 0
B106: 01.02.03.18 | C106: CO253 | D106: CONTROLE TECNOLOGICO DO CONCRETO (ESTRUTURA) | E106: SERVIÇO | F106: 4 | G106: 01.002.003.018 | H106: =IF(F106=4,B106&" - "&C106,"") -> 01.02.03.18 - CO253 | J106: =IF(F106=4,SUMIFS(Tabela1[PAGO],Tabela1[CHAVE],'Controle EAP'!H106),SUMIFS(J:J,$G:$G,'Controle EAP'!G106&"????")) -> 0 | K106: =I106-J106 -> 0
B107: 01.02.03.19 | C107: CO028 | D107: CONFECÇÃO DE FORMA CONTENÇÃO | E107: SERVIÇO | F107: 4 | G107: 01.002.003.019 | H107: =IF(F107=4,B107&" - "&C107,"") -> 01.02.03.19 - CO028 | J107: =IF(F107=4,SUMIFS(Tabela1[PAGO],Tabela1[CHAVE],'Controle EAP'!H107),SUMIFS(J:J,$G:$G,'Controle EAP'!G107&"????")) -> 0 | K107: =I107-J107 -> 0
B108: 01.02.04 | C108: -1 | D108: ESTRUTURA | E108: FASE | F108: 3 | G108: 01.002.004 | H108: =IF(F108=4,B108&" - "&C108,"") | I108: =SUMIFS(I:I,$G:$G,'Controle EAP'!G108&"????") -> 0 | J108: =IF(F108=4,SUMIFS(Tabela1[PAGO],Tabela1[CHAVE],'Controle EAP'!H108),SUMIFS(J:J,$G:$G,'Controle EAP'!G108&"????")) -> 0 | K108: =I108-J108 -> 0
B109: 01.02.04.01 | C109: C14427 | D109: SERVIÇO DE EXECUÇÃO DE CONFECÇÃO DE FORMA | E109: SERVIÇO | F109: 4 | G109: 01.002.004.001 | H109: =IF(F109=4,B109&" - "&C109,"") -> 01.02.04.01 - C14427 | I109: 0 | J109: =IF(F109=4,SUMIFS(Tabela1[PAGO],Tabela1[CHAVE],'Controle EAP'!H109),SUMIFS(J:J,$G:$G,'Controle EAP'!G109&"????")) -> 0 | K109: =I109-J109 -> 0
B110: 01.02.04.02 | C110: CO432 | D110: MONTAGEM/DESMONTAGEM DE FORMA | E110: SERVIÇO | F110: 4 | G110: 01.002.004.002 | H110: =IF(F110=4,B110&" - "&C110,"") -> 01.02.04.02 - CO432 | I110: 0 | J110: =IF(F110=4,SUMIFS(Tabela1[PAGO],Tabela1[CHAVE],'Controle EAP'!H110),SUMIFS(J:J,$G:$G,'Controle EAP'!G110&"????")) -> 0 | K110: =I110-J110 -> 0
B111: 01.02.04.03 | C111: CO430 | D111: CORTE, DOBRA E MONTAGEM DE AÇO | E111: SERVIÇO | F111: 4 | G111: 01.002.004.003 | H111: =IF(F111=4,B111&" - "&C111,"") -> 01.02.04.03 - CO430 | I111: 0 | J111: =IF(F111=4,SUMIFS(Tabela1[PAGO],Tabela1[CHAVE],'Controle EAP'!H111),SUMIFS(J:J,$G:$G,'Controle EAP'!G111&"????")) -> 0 | K111: =I111-J111 -> 0
B112: 01.02.04.04 | C112: CO071 | D112: CONCRETO USINADO BOMBEÁVEL FCK 40 MPA, BRITA 0 E SLUMP 22+-3 | E112: SERVIÇO | F112: 4 | G112: 01.002.004.004 | H112: =IF(F112=4,B112&" - "&C112,"") -> 01.02.04.04 - CO071 | I112: 0 | J112: =IF(F112=4,SUMIFS(Tabela1[PAGO],Tabela1[CHAVE],'Controle EAP'!H112),SUMIFS(J:J,$G:$G,'Controle EAP'!G112&"????")) -> 0 | K112: =I112-J112 -> 0
B113: 01.02.04.05 | C113: CO078 | D113: TAXA DE BOMBA DE CONCRETO ATÉ A 35º LAJE | E113: SERVIÇO | F113: 4 | G113: 01.002.004.005 | H113: =IF(F113=4,B113&" - "&C113,"") -> 01.02.04.05 - CO078 | I113: 0 | J113: =IF(F113=4,SUMIFS(Tabela1[PAGO],Tabela1[CHAVE],'Controle EAP'!H113),SUMIFS(J:J,$G:$G,'Controle EAP'!G113&"????")) -> 0 | K113: =I113-J113 -> 0
B114: 01.02.04.06 | C114: CO552 | D114: LANÇAMENTO DE CONCRETO PISO VASSOURADO | E114: SERVIÇO | F114: 4 | G114: 01.002.004.006 | H114: =IF(F114=4,B114&" - "&C114,"") -> 01.02.04.06 - CO552 | I114: 0 | J114: =IF(F114=4,SUMIFS(Tabela1[PAGO],Tabela1[CHAVE],'Controle EAP'!H114),SUMIFS(J:J,$G:$G,'Controle EAP'!G114&"????")) -> 0 | K114: =I114-J114 -> 0
B115: 01.02.04.07 | C115: CO253 | D115: CONTROLE TECNOLOGICO DO CONCRETO (ESTRUTURA) | E115: SERVIÇO | F115: 4 | G115: 01.002.004.007 | H115: =IF(F115=4,B115&" - "&C115,"") -> 01.02.04.07 - CO253 | I115: 0 | J115: =IF(F115=4,SUMIFS(Tabela1[PAGO],Tabela1[CHAVE],'Controle EAP'!H115),SUMIFS(J:J,$G:$G,'Controle EAP'!G115&"????")) -> 0 | K115: =I115-J115 -> 0
B116: 01.02.04.08 | C116: C18745 | D116: IMPERMEABILIZAÇÃO DE BALDRAME | E116: SERVIÇO | F116: 4 | G116: 01.002.004.008 | H116: =IF(F116=4,B116&" - "&C116,"") -> 01.02.04.08 - C18745 | I116: 0 | J116: =IF(F116=4,SUMIFS(Tabela1[PAGO],Tabela1[CHAVE],'Controle EAP'!H116),SUMIFS(J:J,$G:$G,'Controle EAP'!G116&"????")) -> 0 | K116: =I116-J116 -> 0
B117: 01.02.04.09 | C117: CO062 | D117: REATERRO COMPACTADO | E117: SERVIÇO | F117: 4 | G117: 01.002.004.009 | H117: =IF(F117=4,B117&" - "&C117,"") -> 01.02.04.09 - CO062 | I117: 0 | J117: =IF(F117=4,SUMIFS(Tabela1[PAGO],Tabela1[CHAVE],'Controle EAP'!H117),SUMIFS(J:J,$G:$G,'Controle EAP'!G117&"????")) -> 0 | K117: =I117-J117 -> 0
B118: 01.02.04.10 | C118: C15721 | D118: SERVIÇO DE EXECUÇÃO DE MONTAGEM DE ESTRUTURA METÁLICA | E118: SERVIÇO | F118: 4 | G118: 01.002.004.010 | H118: =IF(F118=4,B118&" - "&C118,"") -> 01.02.04.10 - C15721 | I118: 0 | J118: =IF(F118=4,SUMIFS(Tabela1[PAGO],Tabela1[CHAVE],'Controle EAP'!H118),SUMIFS(J:J,$G:$G,'Controle EAP'!G118&"????")) -> 0 | K118: =I118-J118 -> 0
B119: 01.02.04.11 | C119: C15721 | D119: SERVIÇO DE EXECUÇÃO DE MONTAGEM DE ESTRUTURA METÁLICA | E119: SERVIÇO | F119: 4 | G119: 01.002.004.011 | H119: =IF(F119=4,B119&" - "&C119,"") -> 01.02.04.11 - C15721 | I119: 0 | J119: =IF(F119=4,SUMIFS(Tabela1[PAGO],Tabela1[CHAVE],'Controle EAP'!H119),SUMIFS(J:J,$G:$G,'Controle EAP'!G119&"????")) -> 0 | K119: =I119-J119 -> 0
B120: 01.02.04.12 | C120: C19931 | D120: DEMOLIÇÃO DE ESTRUTRURA METÁLICA | E120: SERVIÇO | F120: 4 | G120: 01.002.004.012 | H120: =IF(F120=4,B120&" - "&C120,"") -> 01.02.04.12 - C19931 | I120: 0 | J120: =IF(F120=4,SUMIFS(Tabela1[PAGO],Tabela1[CHAVE],'Controle EAP'!H120),SUMIFS(J:J,$G:$G,'Controle EAP'!G120&"????")) -> 0 | K120: =I120-J120 -> 0
B121: 01.02.05 | C121: -1 | D121: PAREDES/VEDAÇÕES | E121: FASE | F121: 3 | G121: 01.002.005 | H121: =IF(F121=4,B121&" - "&C121,"") | I121: =SUMIFS(I:I,$G:$G,'Controle EAP'!G121&"????") -> 0 | J121: =IF(F121=4,SUMIFS(Tabela1[PAGO],Tabela1[CHAVE],'Controle EAP'!H121),SUMIFS(J:J,$G:$G,'Controle EAP'!G121&"????")) -> 0 | K121: =I121-J121 -> 0
B122: 01.02.05.01 | C122: CO085 | D122: ALV. DE TIJOLO CER. FURADO 14X19X29 CM | E122: SERVIÇO | F122: 4 | G122: 01.002.005.001 | H122: =IF(F122=4,B122&" - "&C122,"") -> 01.02.05.01 - CO085 | I122: 0 | J122: =IF(F122=4,SUMIFS(Tabela1[PAGO],Tabela1[CHAVE],'Controle EAP'!H122),SUMIFS(J:J,$G:$G,'Controle EAP'!G122&"????")) -> 0 | K122: =I122-J122 -> 0
B123: 01.02.05.02 | C123: CO082 | D123: MARCAÇÃO DE ALVENARIA | E123: SERVIÇO | F123: 4 | G123: 01.002.005.002 | H123: =IF(F123=4,B123&" - "&C123,"") -> 01.02.05.02 - CO082 | I123: 0 | J123: =IF(F123=4,SUMIFS(Tabela1[PAGO],Tabela1[CHAVE],'Controle EAP'!H123),SUMIFS(J:J,$G:$G,'Controle EAP'!G123&"????")) -> 0 | K123: =I123-J123 -> 0
B124: 01.02.05.03 | C124: C15146 | D124: SERVIÇO DE EXECUÇÃO DE ENCUNHAMENTO DE ALVENARIA | E124: SERVIÇO | F124: 4 | G124: 01.002.005.003 | H124: =IF(F124=4,B124&" - "&C124,"") -> 01.02.05.03 - C15146 | I124: 0 | J124: =IF(F124=4,SUMIFS(Tabela1[PAGO],Tabela1[CHAVE],'Controle EAP'!H124),SUMIFS(J:J,$G:$G,'Controle EAP'!G124&"????")) -> 0 | K124: =I124-J124 -> 0
B125: 01.02.05.04 | C125: CO089 | D125: VERGA DE CONCRETO | E125: SERVIÇO | F125: 4 | G125: 01.002.005.004 | H125: =IF(F125=4,B125&" - "&C125,"") -> 01.02.05.04 - CO089 | I125: 0 | J125: =IF(F125=4,SUMIFS(Tabela1[PAGO],Tabela1[CHAVE],'Controle EAP'!H125),SUMIFS(J:J,$G:$G,'Controle EAP'!G125&"????")) -> 0 | K125: =I125-J125 -> 0
B126: 01.02.05.05 | C126: CO090 | D126: CONTRAVERGA EM CONCRETO | E126: SERVIÇO | F126: 4 | G126: 01.002.005.005 | H126: =IF(F126=4,B126&" - "&C126,"") -> 01.02.05.05 - CO090 | I126: 0 | J126: =IF(F126=4,SUMIFS(Tabela1[PAGO],Tabela1[CHAVE],'Controle EAP'!H126),SUMIFS(J:J,$G:$G,'Controle EAP'!G126&"????")) -> 0 | K126: =I126-J126 -> 0
B127: 01.02.05.06 | C127: C19932 | D127: PAREDE DE DRY WALL 7CM | E127: SERVIÇO | F127: 4 | G127: 01.002.005.006 | H127: =IF(F127=4,B127&" - "&C127,"") -> 01.02.05.06 - C19932 | I127: 0 | J127: =IF(F127=4,SUMIFS(Tabela1[PAGO],Tabela1[CHAVE],'Controle EAP'!H127),SUMIFS(J:J,$G:$G,'Controle EAP'!G127&"????")) -> 0 | K127: =I127-J127 -> 0
B128: 01.02.05.07 | C128: C13274 | D128: SERVIÇO DE EXECUÇÃO DE GESSO ACARTONADO - SHAFT COM PLACA ST | E128: SERVIÇO | F128: 4 | G128: 01.002.005.007 | H128: =IF(F128=4,B128&" - "&C128,"") -> 01.02.05.07 - C13274 | I128: 0 | J128: =IF(F128=4,SUMIFS(Tabela1[PAGO],Tabela1[CHAVE],'Controle EAP'!H128),SUMIFS(J:J,$G:$G,'Controle EAP'!G128&"????")) -> 0 | K128: =I128-J128 -> 0
B129: 01.02.05.08 | C129: C13272 | D129: SERVIÇO DE EXECUÇÃO DE GESSO ACARTONADO - SHAFT COM PLACA RU | E129: SERVIÇO | F129: 4 | G129: 01.002.005.008 | H129: =IF(F129=4,B129&" - "&C129,"") -> 01.02.05.08 - C13272 | I129: 0 | J129: =IF(F129=4,SUMIFS(Tabela1[PAGO],Tabela1[CHAVE],'Controle EAP'!H129),SUMIFS(J:J,$G:$G,'Controle EAP'!G129&"????")) -> 0 | K129: =I129-J129 -> 0
B130: 01.02.05.09 | C130: C19654 | D130: SERVIÇO DE EXECUÇÃO DE DRYWALL EM PAREDE DUPLA 70MM - PLACA ST/RU | E130: SERVIÇO | F130: 4 | G130: 01.002.005.009 | H130: =IF(F130=4,B130&" - "&C130,"") -> 01.02.05.09 - C19654 | I130: 0 | J130: =IF(F130=4,SUMIFS(Tabela1[PAGO],Tabela1[CHAVE],'Controle EAP'!H130),SUMIFS(J:J,$G:$G,'Controle EAP'!G130&"????")) -> 0 | K130: =I130-J130 -> 0
B131: 01.02.05.10 | C131: CO215 | D131: PAINEL FITNESS | E131: SERVIÇO | F131: 4 | G131: 01.002.005.010 | H131: =IF(F131=4,B131&" - "&C131,"") -> 01.02.05.10 - CO215 | I131: 0 | J131: =IF(F131=4,SUMIFS(Tabela1[PAGO],Tabela1[CHAVE],'Controle EAP'!H131),SUMIFS(J:J,$G:$G,'Controle EAP'!G131&"????")) -> 0 | K131: =I131-J131 -> 0
B132: 01.02.06 | C132: -1 | D132: ESQUADRIAS DE MADEIRA | E132: FASE | F132: 3 | G132: 01.002.006 | H132: =IF(F132=4,B132&" - "&C132,"") | I132: =SUMIFS(I:I,$G:$G,'Controle EAP'!G132&"????") -> 0 | J132: =IF(F132=4,SUMIFS(Tabela1[PAGO],Tabela1[CHAVE],'Controle EAP'!H132),SUMIFS(J:J,$G:$G,'Controle EAP'!G132&"????")) -> 0 | K132: =I132-J132 -> 0
...

Sheet Detalhado
B3: PROCESSOS DE PAGAMENTO LANÇADOS NO UAU | P3: CONTRATOS LANÇADOS NO UAU | AB3: CONTAS A LANÇAR – GERENCIAL (PREVISTAS, AINDA NÃO LANÇADAS)
K4: =SUM(Tabela1[PAGO]) -> 0 | L4: =SUM(Tabela1[A_PAGAR]) -> 0 | W4: =SUM(Tabela2[TOTAL DO CONTRATO]) -> 0 | X4: =SUM(Tabela2[TOTAL APROVADO]) -> 0 | Y4: =SUM(Tabela2[TOTAL SALDO]) -> 0
B5: ATUALIZACAO | C5: EMPRESA | D5: OBRA | E5: ITEM_PL | F5: SERVICO | G5: INSUMO | H5: FORNECEDOR | I5: PROCESSO | J5: DATA_DE_PAGAMENTO | K5: PAGO | L5: A_PAGAR | M5: DATA_GERACAO | N5: CHAVE | P5: EMPRESA | Q5: OBRA | R5: SERVIÇO | S5: INSUMO | T5: FORNECEDOR | U5: ITEM PL | V5: CONTRATO | W5: TOTAL DO CONTRATO | X5: TOTAL APROVADO | Y5: TOTAL SALDO | AB5: ITEM | AC5: ALOCAÇÃO | AD5: VALOR PREVISTO
B6: 46244 | C6: 000 - EMPRESA EXEMPLO LTDA | D6: OBRA EXEMPLO - CUSTO DE OBRA | E6: 01.01.02.01 | F6: C18698 - BARRACÕES DE OBRA | G6: I19120 - MATERIAL DE APOIO | H6: 000 - FORNECEDOR EXEMPLO | I6: 46039 | J6: 46268 | K6: 0 | L6: 0 | M6: 46240 | N6: =_xlfn.CONCAT(Tabela1[[#This Row],[ITEM_PL]]," - ",MID(Tabela1[[#This Row],[SERVICO]],1,SEARCH(" ",Tabela1[[#This Row],[SERVICO]],1)-1)) -> 01.01.02.01 - C18698 | P6: 000 - EMPRESA EXEMPLO LTDA | Q6: OBRA EXEMPLO - CUSTO DE OBRA | R6: C17211 - INSTALAÇÕES DE CANTEIRO | S6: TC0351 - SERVICOS GERAIS | T6: 000 - FORNECEDOR EXEMPLO | U6: 01.01.02.07 | V6: 3 | W6: 0 | X6: 0 | Y6: 0
B7: 46244 | C7: 000 - EMPRESA EXEMPLO LTDA | D7: OBRA EXEMPLO - CUSTO DE OBRA | E7: 01.01.02.01 | F7: C18698 - BARRACÕES DE OBRA | G7: TC0351 - SERVICOS GERAIS | H7: 000 - FORNECEDOR EXEMPLO | I7: 46025 | J7: 46245 | K7: 0 | L7: 0 | M7: 46232 | N7: =_xlfn.CONCAT(Tabela1[[#This Row],[ITEM_PL]]," - ",MID(Tabela1[[#This Row],[SERVICO]],1,SEARCH(" ",Tabela1[[#This Row],[SERVICO]],1)-1)) -> 01.01.02.01 - C18698 | P7: 000 - EMPRESA EXEMPLO LTDA | Q7: OBRA EXEMPLO - CUSTO DE OBRA | R7: CSF7.04 - DEMOLIÇÃO. | S7: TC0351 - SERVICOS GERAIS | T7: 000 - FORNECEDOR EXEMPLO | U7: 01.02.00.03 | V7: 1 | W7: 0 | X7: 0 | Y7: 0
B8: 46244 | C8: 000 - EMPRESA EXEMPLO LTDA | D8: OBRA EXEMPLO - CUSTO DE OBRA | E8: 01.01.04.02 | F8: CO454 - GERENTE DE OBRA | G8: I19120 - MATERIAL DE APOIO | H8: 000 - FORNECEDOR EXEMPLO | I8: 46041 | J8: 46248 | K8: 0 | L8: 0 | M8: 46241 | N8: =_xlfn.CONCAT(Tabela1[[#This Row],[ITEM_PL]]," - ",MID(Tabela1[[#This Row],[SERVICO]],1,SEARCH(" ",Tabela1[[#This Row],[SERVICO]],1)-1)) -> 01.01.04.02 - CO454 | P8: 000 - EMPRESA EXEMPLO LTDA | Q8: OBRA EXEMPLO - CUSTO DE OBRA | R8: C00756 - GERENCIAMENTO DE OBRA | S8: I19849 - DESPESAS CONTABEIS | T8: 000 - FORNECEDOR EXEMPLO | U8: 01.04.03.01 | V8: 4 | W8: 0 | X8: 0 | Y8: 0
B9: 46244 | C9: 000 - EMPRESA EXEMPLO LTDA | D9: OBRA EXEMPLO - CUSTO DE OBRA | E9: 01.01.01.01 | F9: C18612 - SERVIÇO DE ELABORAÇÃO DE MANUAL DO PROPRIETÁRIO | G9: I38849 - SEGURO DE OBRA | H9: 000 - FORNECEDOR EXEMPLO | I9: 46060 | J9: 46232 | K9: 0 | L9: 0 | M9: 46232 | N9: =_xlfn.CONCAT(Tabela1[[#This Row],[ITEM_PL]]," - ",MID(Tabela1[[#This Row],[SERVICO]],1,SEARCH(" ",Tabela1[[#This Row],[SERVICO]],1)-1)) -> 01.01.01.01 - C18612 | P9: 000 - EMPRESA EXEMPLO LTDA | Q9: OBRA EXEMPLO - CUSTO DE OBRA | R9: C00756 - GERENCIAMENTO DE OBRA | S9: TC0351 - SERVICOS GERAIS | T9: 000 - FORNECEDOR EXEMPLO | U9: 01.04.03.01 | V9: 2 | W9: 0 | X9: 0 | Y9: 0
B10: 46244 | C10: 000 - EMPRESA EXEMPLO LTDA | D10: OBRA EXEMPLO - CUSTO DE OBRA | E10: 01.02.00.03 | F10: CSF7.04 - DEMOLIÇÃO. | G10: TC0351 - SERVICOS GERAIS | H10: 000 - FORNECEDOR EXEMPLO | I10: 46037 | J10: 46240 | K10: 0 | L10: 0 | M10: 46233 | N10: =_xlfn.CONCAT(Tabela1[[#This Row],[ITEM_PL]]," - ",MID(Tabela1[[#This Row],[SERVICO]],1,SEARCH(" ",Tabela1[[#This Row],[SERVICO]],1)-1)) -> 01.02.00.03 - CSF7.04
B11: 46244 | C11: 000 - EMPRESA EXEMPLO LTDA | D11: OBRA EXEMPLO - CUSTO DE OBRA | E11: 01.01.01.01 | F11: C18612 - SERVIÇO DE ELABORAÇÃO DE MANUAL DO PROPRIETÁRIO | G11: I38849 - SEGURO DE OBRA | H11: 000 - FORNECEDOR EXEMPLO | I11: 46088 | J11: 46261 | K11: 0 | L11: 0 | M11: 46232 | N11: =_xlfn.CONCAT(Tabela1[[#This Row],[ITEM_PL]]," - ",MID(Tabela1[[#This Row],[SERVICO]],1,SEARCH(" ",Tabela1[[#This Row],[SERVICO]],1)-1)) -> 01.01.01.01 - C18612
B12: 46244 | C12: 000 - EMPRESA EXEMPLO LTDA | D12: OBRA EXEMPLO - CUSTO DE OBRA | E12: 01.01.01.01 | F12: C18612 - SERVIÇO DE ELABORAÇÃO DE MANUAL DO PROPRIETÁRIO | G12: I38849 - SEGURO DE OBRA | H12: 000 - FORNECEDOR EXEMPLO | I12: 46119 | J12: 46293 | K12: 0 | L12: 0 | M12: 46232 | N12: =_xlfn.CONCAT(Tabela1[[#This Row],[ITEM_PL]]," - ",MID(Tabela1[[#This Row],[SERVICO]],1,SEARCH(" ",Tabela1[[#This Row],[SERVICO]],1)-1)) -> 01.01.01.01 - C18612
B13: 46244 | C13: 000 - EMPRESA EXEMPLO LTDA | D13: OBRA EXEMPLO - CUSTO DE OBRA | E13: 01.01.02.07 | F13: C17211 - INSTALAÇÕES DE CANTEIRO | G13: TC0351 - SERVICOS GERAIS | H13: 000 - FORNECEDOR EXEMPLO | I13: 46040 | J13: 46248 | K13: 0 | L13: 0 | M13: 46241 | N13: =_xlfn.CONCAT(Tabela1[[#This Row],[ITEM_PL]]," - ",MID(Tabela1[[#This Row],[SERVICO]],1,SEARCH(" ",Tabela1[[#This Row],[SERVICO]],1)-1)) -> 01.01.02.07 - C17211
B14: 46244 | C14: 000 - EMPRESA EXEMPLO LTDA | D14: OBRA EXEMPLO - CUSTO DE OBRA | E14: 01.02.00.03 | F14: CSF7.04 - DEMOLIÇÃO. | G14: I19120 - MATERIAL DE APOIO | H14: 000 - FORNECEDOR EXEMPLO | I14: 46038 | J14: 46247 | K14: 0 | L14: 0 | M14: 46239 | N14: =_xlfn.CONCAT(Tabela1[[#This Row],[ITEM_PL]]," - ",MID(Tabela1[[#This Row],[SERVICO]],1,SEARCH(" ",Tabela1[[#This Row],[SERVICO]],1)-1)) -> 01.02.00.03 - CSF7.04
B15: 46244 | C15: 000 - EMPRESA EXEMPLO LTDA | D15: OBRA EXEMPLO - CUSTO DE OBRA | E15: 01.01.01.01 | F15: C18612 - SERVIÇO DE ELABORAÇÃO DE MANUAL DO PROPRIETÁRIO | G15: I38849 - SEGURO DE OBRA | H15: 000 - FORNECEDOR EXEMPLO | I15: 46149 | J15: 46322 | K15: 0 | L15: 0 | M15: 46232 | N15: =_xlfn.CONCAT(Tabela1[[#This Row],[ITEM_PL]]," - ",MID(Tabela1[[#This Row],[SERVICO]],1,SEARCH(" ",Tabela1[[#This Row],[SERVICO]],1)-1)) -> 01.01.01.01 - C18612
